trackerstatus/__init__.py
trackerstatus/core.py
trackerstatus/endpoints/__init__.py
trackerstatus/endpoints/ant.py
trackerstatus/endpoints/ar.py
trackerstatus/endpoints/base.py
trackerstatus/endpoints/btn.py
trackerstatus/endpoints/ggn.py
trackerstatus/endpoints/nbl.py
trackerstatus/endpoints/ops.py
trackerstatus/endpoints/ptp.py
trackerstatus/endpoints/red.py
trackerstatus/endpoints/status.py
trackerstatus-1.0.10.dist-info/LICENSE
trackerstatus-1.0.10.dist-info/METADATA
trackerstatus-1.0.10.dist-info/WHEEL
trackerstatus-1.0.10.dist-info/RECORD
