Metadata-Version: 2.3
Name: trackerstatus
Version: 1.0.10
Summary: A Python client for the trackerstatus.info API
License: MIT
Keywords: tracker,status,api,client
Author: mauvehed
Author-email: nate@mvh.dev
Maintainer: mauvehed
Maintainer-email: nate@mvh.dev
Requires-Python: >=3.9
Classifier: Development Status :: 5 - Production/Stable
Classifier: Intended Audience :: Developers
Classifier: License :: OSI Approved :: MIT License
Classifier: Programming Language :: Python :: 3
Classifier: Programming Language :: Python :: 3.9
Classifier: Programming Language :: Python :: 3.10
Classifier: Programming Language :: Python :: 3.11
Requires-Dist: requests (>=2.31.0)
Project-URL: Documentation, https://github.com/mauvehed/trackerstatus/blob/main/docs/API.md
Project-URL: Homepage, https://github.com/mauvehed/trackerstatus
Project-URL: Repository, https://github.com/mauvehed/trackerstatus
